<?xml version="1.0" encoding="UTF-8"?>
<brendovi>
	<brend>
		<id>1</id>
		<BrendIme>3G</BrendIme>
		<BrendLink>3g</BrendLink>
		<pictureUrl>3g.png</pictureUrl>
		<BrendOpis>gsdg</BrendOpis>
		<BrendActive>1</BrendActive>
		<BrendNaslovna>0</BrendNaslovna>
	</brend>
	<brend>
		<id>2</id>
		<BrendIme>Giulietta</BrendIme>
		<BrendLink>giulietta</BrendLink>
		<pictureUrl></pictureUrl>
		<BrendOpis></BrendOpis>
		<BrendActive>0</BrendActive>
		<BrendNaslovna>0</BrendNaslovna>
	</brend>
	<brend>
		<id>3</id>
		<BrendIme>Nillkin</BrendIme>
		<BrendLink>nillkin</BrendLink>
		<pictureUrl>nillkin.png</pictureUrl>
		<BrendOpis></BrendOpis>
		<BrendActive>1</BrendActive>
		<BrendNaslovna>0</BrendNaslovna>
	</brend>
	<brend>
		<id>4</id>
		<BrendIme>iPhone</BrendIme>
		<BrendLink>iphone</BrendLink>
		<pictureUrl>iphone.png</pictureUrl>
		<BrendOpis></BrendOpis>
		<BrendActive>1</BrendActive>
		<BrendNaslovna>1</BrendNaslovna>
	</brend>
	<brend>
		<id>5</id>
		<BrendIme>Samsung</BrendIme>
		<BrendLink>samsung</BrendLink>
		<pictureUrl>samsung.png</pictureUrl>
		<BrendOpis></BrendOpis>
		<BrendActive>1</BrendActive>
		<BrendNaslovna>1</BrendNaslovna>
	</brend>
	<brend>
		<id>6</id>
		<BrendIme>Sony</BrendIme>
		<BrendLink>sony</BrendLink>
		<pictureUrl>sony.png</pictureUrl>
		<BrendOpis></BrendOpis>
		<BrendActive>1</BrendActive>
		<BrendNaslovna>1</BrendNaslovna>
	</brend>
	<brend>
		<id>7</id>
		<BrendIme>Nokia</BrendIme>
		<BrendLink>nokia</BrendLink>
		<pictureUrl>nokia.png</pictureUrl>
		<BrendOpis></BrendOpis>
		<BrendActive>1</BrendActive>
		<BrendNaslovna>1</BrendNaslovna>
	</brend>
	<brend>
		<id>8</id>
		<BrendIme>LG</BrendIme>
		<BrendLink>lg</BrendLink>
		<pictureUrl>lg.png</pictureUrl>
		<BrendOpis></BrendOpis>
		<BrendActive>1</BrendActive>
		<BrendNaslovna>1</BrendNaslovna>
	</brend>
	<brend>
		<id>9</id>
		<BrendIme>ZTE</BrendIme>
		<BrendLink>zte</BrendLink>
		<pictureUrl>zte.png</pictureUrl>
		<BrendOpis></BrendOpis>
		<BrendActive>1</BrendActive>
		<BrendNaslovna>1</BrendNaslovna>
	</brend>
	<brend>
		<id>10</id>
		<BrendIme>HTC</BrendIme>
		<BrendLink>htc</BrendLink>
		<pictureUrl>htc.png</pictureUrl>
		<BrendOpis></BrendOpis>
		<BrendActive>1</BrendActive>
		<BrendNaslovna>1</BrendNaslovna>
	</brend>
	<brend>
		<id>11</id>
		<BrendIme>Alcatel</BrendIme>
		<BrendLink>alcatel</BrendLink>
		<pictureUrl>alcatel.png</pictureUrl>
		<BrendOpis></BrendOpis>
		<BrendActive>1</BrendActive>
		<BrendNaslovna>1</BrendNaslovna>
	</brend>
	<brend>
		<id>12</id>
		<BrendIme>Huawei</BrendIme>
		<BrendLink>huawei</BrendLink>
		<pictureUrl>huawei.png</pictureUrl>
		<BrendOpis></BrendOpis>
		<BrendActive>1</BrendActive>
		<BrendNaslovna>1</BrendNaslovna>
	</brend>
	<brend>
		<id>13</id>
		<BrendIme>BlackBerry</BrendIme>
		<BrendLink>blackberry</BrendLink>
		<pictureUrl>blackberry.png</pictureUrl>
		<BrendOpis></BrendOpis>
		<BrendActive>1</BrendActive>
		<BrendNaslovna>1</BrendNaslovna>
	</brend>
	<brend>
		<id>14</id>
		<BrendIme>Jekod</BrendIme>
		<BrendLink>jekod</BrendLink>
		<pictureUrl>jekod.png</pictureUrl>
		<BrendOpis></BrendOpis>
		<BrendActive>1</BrendActive>
		<BrendNaslovna>0</BrendNaslovna>
	</brend>
	<brend>
		<id>15</id>
		<BrendIme>Teracell</BrendIme>
		<BrendLink>teracell</BrendLink>
		<pictureUrl>teracell.png</pictureUrl>
		<BrendOpis></BrendOpis>
		<BrendActive>1</BrendActive>
		<BrendNaslovna>0</BrendNaslovna>
	</brend>
	<brend>
		<id>16</id>
		<BrendIme>ITSKINS</BrendIme>
		<BrendLink>itskins</BrendLink>
		<pictureUrl>itskins.png</pictureUrl>
		<BrendOpis></BrendOpis>
		<BrendActive>1</BrendActive>
		<BrendNaslovna>0</BrendNaslovna>
	</brend>
	<brend>
		<id>17</id>
		<BrendIme>Capdase</BrendIme>
		<BrendLink>capdase</BrendLink>
		<pictureUrl>capdase.png</pictureUrl>
		<BrendOpis></BrendOpis>
		<BrendActive>1</BrendActive>
		<BrendNaslovna>0</BrendNaslovna>
	</brend>
	<brend>
		<id>18</id>
		<BrendIme>Bluetooth</BrendIme>
		<BrendLink>bluetooth</BrendLink>
		<pictureUrl>bluetooth.png</pictureUrl>
		<BrendOpis></BrendOpis>
		<BrendActive>1</BrendActive>
		<BrendNaslovna>0</BrendNaslovna>
	</brend>
	<brend>
		<id>19</id>
		<BrendIme>Prestigio</BrendIme>
		<BrendLink>prestigio</BrendLink>
		<pictureUrl>prestigio.png</pictureUrl>
		<BrendOpis></BrendOpis>
		<BrendActive>1</BrendActive>
		<BrendNaslovna>1</BrendNaslovna>
	</brend>
	<brend>
		<id>20</id>
		<BrendIme>Acer</BrendIme>
		<BrendLink>acer</BrendLink>
		<pictureUrl>acer.png</pictureUrl>
		<BrendOpis></BrendOpis>
		<BrendActive>1</BrendActive>
		<BrendNaslovna>1</BrendNaslovna>
	</brend>
	<brend>
		<id>21</id>
		<BrendIme>Lenovo</BrendIme>
		<BrendLink>lenovo</BrendLink>
		<pictureUrl>lenovo.png</pictureUrl>
		<BrendOpis></BrendOpis>
		<BrendActive>1</BrendActive>
		<BrendNaslovna>1</BrendNaslovna>
	</brend>
	<brend>
		<id>22</id>
		<BrendIme>Ebai</BrendIme>
		<BrendLink>ebai</BrendLink>
		<pictureUrl>ebai.png</pictureUrl>
		<BrendOpis>Backup baterije</BrendOpis>
		<BrendActive>1</BrendActive>
		<BrendNaslovna>0</BrendNaslovna>
	</brend>
	<brend>
		<id>25</id>
		<BrendIme>Nema</BrendIme>
		<BrendLink>#</BrendLink>
		<pictureUrl></pictureUrl>
		<BrendOpis>Nema</BrendOpis>
		<BrendActive>0</BrendActive>
		<BrendNaslovna>0</BrendNaslovna>
	</brend>
	<brend>
		<id>26</id>
		<BrendIme>Otterbox</BrendIme>
		<BrendLink>otterbox</BrendLink>
		<pictureUrl>otterbox.png</pictureUrl>
		<BrendOpis></BrendOpis>
		<BrendActive>1</BrendActive>
		<BrendNaslovna>0</BrendNaslovna>
	</brend>
	<brend>
		<id>27</id>
		<BrendIme>Speck</BrendIme>
		<BrendLink>speck</BrendLink>
		<pictureUrl>speck.png</pictureUrl>
		<BrendOpis></BrendOpis>
		<BrendActive>1</BrendActive>
		<BrendNaslovna>0</BrendNaslovna>
	</brend>
	<brend>
		<id>28</id>
		<BrendIme>Puro</BrendIme>
		<BrendLink>puro</BrendLink>
		<pictureUrl>puro.png</pictureUrl>
		<BrendOpis></BrendOpis>
		<BrendActive>1</BrendActive>
		<BrendNaslovna>0</BrendNaslovna>
	</brend>
	<brend>
		<id>29</id>
		<BrendIme>Abercrombie and Fitch</BrendIme>
		<BrendLink>abercrombie--fitch</BrendLink>
		<pictureUrl>abercrombie--fitch.png</pictureUrl>
		<BrendOpis></BrendOpis>
		<BrendActive>1</BrendActive>
		<BrendNaslovna>0</BrendNaslovna>
	</brend>
	<brend>
		<id>30</id>
		<BrendIme>Momax</BrendIme>
		<BrendLink>momax</BrendLink>
		<pictureUrl>momax.png</pictureUrl>
		<BrendOpis></BrendOpis>
		<BrendActive>1</BrendActive>
		<BrendNaslovna>0</BrendNaslovna>
	</brend>
	<brend>
		<id>31</id>
		<BrendIme>Motorola</BrendIme>
		<BrendLink>motorola</BrendLink>
		<pictureUrl>motorola.png</pictureUrl>
		<BrendOpis></BrendOpis>
		<BrendActive>1</BrendActive>
		<BrendNaslovna>1</BrendNaslovna>
	</brend>
	<brend>
		<id>32</id>
		<BrendIme>Asus</BrendIme>
		<BrendLink>asus</BrendLink>
		<pictureUrl>asus.png</pictureUrl>
		<BrendOpis></BrendOpis>
		<BrendActive>1</BrendActive>
		<BrendNaslovna>1</BrendNaslovna>
	</brend>
	<brend>
		<id>33</id>
		<BrendIme>Kingston</BrendIme>
		<BrendLink>kingston</BrendLink>
		<pictureUrl>kingston.png</pictureUrl>
		<BrendOpis></BrendOpis>
		<BrendActive>1</BrendActive>
		<BrendNaslovna>0</BrendNaslovna>
	</brend>
	<brend>
		<id>34</id>
		<BrendIme>Remax</BrendIme>
		<BrendLink>remax</BrendLink>
		<pictureUrl>remax.png</pictureUrl>
		<BrendOpis></BrendOpis>
		<BrendActive>1</BrendActive>
		<BrendNaslovna>0</BrendNaslovna>
	</brend>
	<brend>
		<id>35</id>
		<BrendIme>E Feel</BrendIme>
		<BrendLink>e-feel</BrendLink>
		<pictureUrl>e-feel.png</pictureUrl>
		<BrendOpis></BrendOpis>
		<BrendActive>1</BrendActive>
		<BrendNaslovna>1</BrendNaslovna>
	</brend>
	<brend>
		<id>36</id>
		<BrendIme>Tesla</BrendIme>
		<BrendLink>tesla</BrendLink>
		<pictureUrl>tesla.png</pictureUrl>
		<BrendOpis></BrendOpis>
		<BrendActive>1</BrendActive>
		<BrendNaslovna>1</BrendNaslovna>
	</brend>
	<brend>
		<id>37</id>
		<BrendIme>Vivax</BrendIme>
		<BrendLink>vivax</BrendLink>
		<pictureUrl>vivax.png</pictureUrl>
		<BrendOpis></BrendOpis>
		<BrendActive>1</BrendActive>
		<BrendNaslovna>1</BrendNaslovna>
	</brend>
	<brend>
		<id>38</id>
		<BrendIme>Spigen</BrendIme>
		<BrendLink>spigen</BrendLink>
		<pictureUrl>spigen.png</pictureUrl>
		<BrendOpis></BrendOpis>
		<BrendActive>1</BrendActive>
		<BrendNaslovna>0</BrendNaslovna>
	</brend>
	<brend>
		<id>39</id>
		<BrendIme>Hama</BrendIme>
		<BrendLink>hama</BrendLink>
		<pictureUrl>hama.png</pictureUrl>
		<BrendOpis></BrendOpis>
		<BrendActive>1</BrendActive>
		<BrendNaslovna>1</BrendNaslovna>
	</brend>
	<brend>
		<id>40</id>
		<BrendIme>Sandberg</BrendIme>
		<BrendLink>sandberg</BrendLink>
		<pictureUrl>sandberg.png</pictureUrl>
		<BrendOpis></BrendOpis>
		<BrendActive>1</BrendActive>
		<BrendNaslovna>1</BrendNaslovna>
	</brend>
	<brend>
		<id>41</id>
		<BrendIme>Terabyte</BrendIme>
		<BrendLink>terabyte</BrendLink>
		<pictureUrl>terabyte.png</pictureUrl>
		<BrendOpis></BrendOpis>
		<BrendActive>1</BrendActive>
		<BrendNaslovna>0</BrendNaslovna>
	</brend>
	<brend>
		<id>42</id>
		<BrendIme>Apple</BrendIme>
		<BrendLink>apple</BrendLink>
		<pictureUrl>apple.png</pictureUrl>
		<BrendOpis></BrendOpis>
		<BrendActive>1</BrendActive>
		<BrendNaslovna>1</BrendNaslovna>
	</brend>
	<brend>
		<id>43</id>
		<BrendIme>Utok</BrendIme>
		<BrendLink>utok</BrendLink>
		<pictureUrl>utok.png</pictureUrl>
		<BrendOpis></BrendOpis>
		<BrendActive>1</BrendActive>
		<BrendNaslovna>1</BrendNaslovna>
	</brend>
	<brend>
		<id>45</id>
		<BrendIme>Xiaomi</BrendIme>
		<BrendLink>xiaomi</BrendLink>
		<pictureUrl>xiaomi.png</pictureUrl>
		<BrendOpis></BrendOpis>
		<BrendActive>1</BrendActive>
		<BrendNaslovna>0</BrendNaslovna>
	</brend>
	<brend>
		<id>46</id>
		<BrendIme>motomo</BrendIme>
		<BrendLink>motomo</BrendLink>
		<pictureUrl>motomo.png</pictureUrl>
		<BrendOpis></BrendOpis>
		<BrendActive>1</BrendActive>
		<BrendNaslovna>0</BrendNaslovna>
	</brend>
	<brend>
		<id>47</id>
		<BrendIme>MyWigo</BrendIme>
		<BrendLink>mywigo</BrendLink>
		<pictureUrl>mywigo.png</pictureUrl>
		<BrendOpis></BrendOpis>
		<BrendActive>1</BrendActive>
		<BrendNaslovna>1</BrendNaslovna>
	</brend>
	<brend>
		<id>48</id>
		<BrendIme>Mercury</BrendIme>
		<BrendLink>mercury</BrendLink>
		<pictureUrl>mercury.png</pictureUrl>
		<BrendOpis></BrendOpis>
		<BrendActive>1</BrendActive>
		<BrendNaslovna>0</BrendNaslovna>
	</brend>
	<brend>
		<id>49</id>
		<BrendIme>LDNIO</BrendIme>
		<BrendLink>ldnio</BrendLink>
		<pictureUrl>ldnio.png</pictureUrl>
		<BrendOpis>LDNIO</BrendOpis>
		<BrendActive>1</BrendActive>
		<BrendNaslovna>0</BrendNaslovna>
	</brend>
	<brend>
		<id>50</id>
		<BrendIme>Baseus</BrendIme>
		<BrendLink>baseus</BrendLink>
		<pictureUrl>baseus.png</pictureUrl>
		<BrendOpis></BrendOpis>
		<BrendActive>1</BrendActive>
		<BrendNaslovna>0</BrendNaslovna>
	</brend>
	<brend>
		<id>51</id>
		<BrendIme>Hoco</BrendIme>
		<BrendLink>hoco</BrendLink>
		<pictureUrl>hoco.png</pictureUrl>
		<BrendOpis></BrendOpis>
		<BrendActive>1</BrendActive>
		<BrendNaslovna>0</BrendNaslovna>
	</brend>
	<brend>
		<id>52</id>
		<BrendIme>Coolpad</BrendIme>
		<BrendLink>coolpad</BrendLink>
		<pictureUrl>coolpad.png</pictureUrl>
		<BrendOpis></BrendOpis>
		<BrendActive>1</BrendActive>
		<BrendNaslovna>0</BrendNaslovna>
	</brend>
	<brend>
		<id>53</id>
		<BrendIme>WUW</BrendIme>
		<BrendLink>wuw</BrendLink>
		<pictureUrl>wuw.png</pictureUrl>
		<BrendOpis></BrendOpis>
		<BrendActive>1</BrendActive>
		<BrendNaslovna>0</BrendNaslovna>
	</brend>
	<brend>
		<id>54</id>
		<BrendIme>Benks</BrendIme>
		<BrendLink>benks</BrendLink>
		<pictureUrl>benks.png</pictureUrl>
		<BrendOpis></BrendOpis>
		<BrendActive>1</BrendActive>
		<BrendNaslovna>0</BrendNaslovna>
	</brend>
	<brend>
		<id>55</id>
		<BrendIme>Kavaro</BrendIme>
		<BrendLink>kavaro</BrendLink>
		<pictureUrl>kavaro.png</pictureUrl>
		<BrendOpis></BrendOpis>
		<BrendActive>1</BrendActive>
		<BrendNaslovna>0</BrendNaslovna>
	</brend>
	<brend>
		<id>56</id>
		<BrendIme>Meizu</BrendIme>
		<BrendLink>meizu</BrendLink>
		<pictureUrl>meizu.png</pictureUrl>
		<BrendOpis></BrendOpis>
		<BrendActive>1</BrendActive>
		<BrendNaslovna>0</BrendNaslovna>
	</brend>
	<brend>
		<id>57</id>
		<BrendIme>Wiko</BrendIme>
		<BrendLink>wiko</BrendLink>
		<pictureUrl>wiko.png</pictureUrl>
		<BrendOpis></BrendOpis>
		<BrendActive>1</BrendActive>
		<BrendNaslovna>0</BrendNaslovna>
	</brend>
	<brend>
		<id>58</id>
		<BrendIme>Gotron</BrendIme>
		<BrendLink>gotron</BrendLink>
		<pictureUrl>gotron.png</pictureUrl>
		<BrendOpis></BrendOpis>
		<BrendActive>1</BrendActive>
		<BrendNaslovna>0</BrendNaslovna>
	</brend>
	<brend>
		<id>59</id>
		<BrendIme>iNew</BrendIme>
		<BrendLink>inew</BrendLink>
		<pictureUrl>inew.png</pictureUrl>
		<BrendOpis></BrendOpis>
		<BrendActive>1</BrendActive>
		<BrendNaslovna>0</BrendNaslovna>
	</brend>
	<brend>
		<id>60</id>
		<BrendIme>Transcend</BrendIme>
		<BrendLink>transcend</BrendLink>
		<pictureUrl>transcend.png</pictureUrl>
		<BrendOpis></BrendOpis>
		<BrendActive>1</BrendActive>
		<BrendNaslovna>0</BrendNaslovna>
	</brend>
	<brend>
		<id>61</id>
		<BrendIme>Toshiba</BrendIme>
		<BrendLink>toshiba</BrendLink>
		<pictureUrl>toshiba.png</pictureUrl>
		<BrendOpis></BrendOpis>
		<BrendActive>1</BrendActive>
		<BrendNaslovna>0</BrendNaslovna>
	</brend>
	<brend>
		<id>62</id>
		<BrendIme>JBL</BrendIme>
		<BrendLink>jbl</BrendLink>
		<pictureUrl>jbl.png</pictureUrl>
		<BrendOpis>JBL</BrendOpis>
		<BrendActive>1</BrendActive>
		<BrendNaslovna>0</BrendNaslovna>
	</brend>
</brendovi>
